[
  {
    "tag_name": "entity",
    "ids_to_tags": {
      "1": "B-age",
      "2": "I-age",
      "3": "L-age",
      "4": "U-age",
      "5": "B-brand",
      "6": "I-brand",
      "7": "L-brand",
      "8": "U-brand",
      "9": "B-clothes",
      "10": "I-clothes",
      "11": "L-clothes",
      "12": "U-clothes",
      "13": "B-color",
      "14": "I-color",
      "15": "L-color",
      "16": "U-color",
      "17": "B-female",
      "18": "I-female",
      "19": "L-female",
      "20": "U-female",
      "21": "B-footwear",
      "22": "I-footwear",
      "23": "L-footwear",
      "24": "U-footwear",
      "25": "B-male",
      "26": "I-male",
      "27": "L-male",
      "28": "U-male",
      "29": "B-materials",
      "30": "I-materials",
      "31": "L-materials",
      "32": "U-materials",
      "33": "B-size",
      "34": "I-size",
      "35": "L-size",
      "36": "U-size",
      "37": "B-style",
      "38": "I-style",
      "39": "L-style",
      "40": "U-style",
      "0": "O"
    },
    "tags_to_ids": {
      "B-age": 1,
      "I-age": 2,
      "L-age": 3,
      "U-age": 4,
      "B-brand": 5,
      "I-brand": 6,
      "L-brand": 7,
      "U-brand": 8,
      "B-clothes": 9,
      "I-clothes": 10,
      "L-clothes": 11,
      "U-clothes": 12,
      "B-color": 13,
      "I-color": 14,
      "L-color": 15,
      "U-color": 16,
      "B-female": 17,
      "I-female": 18,
      "L-female": 19,
      "U-female": 20,
      "B-footwear": 21,
      "I-footwear": 22,
      "L-footwear": 23,
      "U-footwear": 24,
      "B-male": 25,
      "I-male": 26,
      "L-male": 27,
      "U-male": 28,
      "B-materials": 29,
      "I-materials": 30,
      "L-materials": 31,
      "U-materials": 32,
      "B-size": 33,
      "I-size": 34,
      "L-size": 35,
      "U-size": 36,
      "B-style": 37,
      "I-style": 38,
      "L-style": 39,
      "U-style": 40,
      "O": 0
    },
    "num_tags": 41
  }
]