{"0": "question/ask_attribute", "1": "question/buy", "2": "question/celebrity", "3": "question/do_not_like_earlier_show_result", "4": "question/do_not_like_n_show_result", "5": "question/do_not_like_show_result", "6": "question/filter_results", "7": "question/go_with", "8": "question/like_earlier_show_result", "9": "question/like_n_show_result", "10": "question/like_show_result", "11": "question/show_orientation", "12": "question/show_similar_to", "13": "question/sort_results", "14": "question/suited_for", "15": "repeat-question/ask_attribute", "16": "repeat-question/celebrity", "17": "repeat-question/go_with", "18": "repeat-question/show_orientation", "19": "repeat-question/suited_for"}